Shapely16ZhongwenWendang/README.md
Shapely16ZhongwenWendang/__init__.py
Shapely16ZhongwenWendang/__main__.py
Shapely16ZhongwenWendang/file.epub
Shapely16ZhongwenWendang/index.html
Shapely16ZhongwenWendang/css/__init__.py
Shapely16ZhongwenWendang/css/annotations.css
Shapely16ZhongwenWendang/css/main.css
Shapely16ZhongwenWendang/css/normalize.css
Shapely16ZhongwenWendang/css/popup.css
Shapely16ZhongwenWendang/font/__init__.py
Shapely16ZhongwenWendang/font/fontello.eot
Shapely16ZhongwenWendang/font/fontello.svg
Shapely16ZhongwenWendang/font/fontello.ttf
Shapely16ZhongwenWendang/font/fontello.woff
Shapely16ZhongwenWendang/img/__init__.py
Shapely16ZhongwenWendang/img/annotator-glyph-sprite.png
Shapely16ZhongwenWendang/img/annotator-icon-sprite.png
Shapely16ZhongwenWendang/img/apple-touch-icon.png
Shapely16ZhongwenWendang/img/cancelfullscreen.png
Shapely16ZhongwenWendang/img/close.png
Shapely16ZhongwenWendang/img/fullscreen.png
Shapely16ZhongwenWendang/img/loader.gif
Shapely16ZhongwenWendang/img/menu-icon.png
Shapely16ZhongwenWendang/img/save.png
Shapely16ZhongwenWendang/img/saved.png
Shapely16ZhongwenWendang/img/settings-s.png
Shapely16ZhongwenWendang/img/settings.png
Shapely16ZhongwenWendang/img/star.png
Shapely16ZhongwenWendang/js/__init__.py
Shapely16ZhongwenWendang/js/epub.js
Shapely16ZhongwenWendang/js/epub.min.js
Shapely16ZhongwenWendang/js/epub.min.map
Shapely16ZhongwenWendang/js/hooks.min.js
Shapely16ZhongwenWendang/js/hooks.min.map
Shapely16ZhongwenWendang/js/reader.js
Shapely16ZhongwenWendang/js/reader.js.map
Shapely16ZhongwenWendang/js/reader.min.js
Shapely16ZhongwenWendang/js/reader.min.map
Shapely16ZhongwenWendang/js/hooks/__init__.py
Shapely16ZhongwenWendang/js/hooks/extensions/__init__.py
Shapely16ZhongwenWendang/js/hooks/extensions/highlight.js
Shapely16ZhongwenWendang/js/libs/__init__.py
Shapely16ZhongwenWendang/js/libs/jquery.min.js
Shapely16ZhongwenWendang/js/libs/localforage.min.js
Shapely16ZhongwenWendang/js/libs/screenfull.js
shapely_1_6_zhongwen_wendang-2024.3.4.0.dist-info/METADATA
shapely_1_6_zhongwen_wendang-2024.3.4.0.dist-info/WHEEL
shapely_1_6_zhongwen_wendang-2024.3.4.0.dist-info/entry_points.txt
shapely_1_6_zhongwen_wendang-2024.3.4.0.dist-info/top_level.txt
shapely_1_6_zhongwen_wendang-2024.3.4.0.dist-info/RECORD
